{
  "schema_version": 1,
  "provider": "hathway",
  "api_url": "https://ispselfcareadmin.hathway.net/api/isp/v1/customer/usagedetails",
  "created_at": "2026-06-18T20:29:27+05:30",
  "updated_at": "2026-06-18T20:38:07+05:30",
  "account": {
    "account_no_masked": "******9102",
    "registered_mobile_no_masked": "******4671",
    "login_device": "web"
  },
  "latest": {
    "timestamp": "2026-06-18T20:38:07+05:30",
    "http_status": 200,
    "duration_ms": 225,
    "request_window": {
      "start_date": "2025-12-31T18:30:00.000Z",
      "end_date": "2026-06-18T15:08:06.940Z",
      "timezone": "Asia/Kolkata"
    },
    "normalized": {
      "total_used": null,
      "download": {
        "path": "data[0].downloaded",
        "label": "Data downloaded",
        "value": "22215090575",
        "display": "22215090575",
        "bytes": 22215090575
      },
      "upload": {
        "path": "data[0].uploaded",
        "label": "Data uploaded",
        "value": "4369204412",
        "display": "4369204412",
        "bytes": 4369204412
      },
      "remaining": null,
      "quota": null,
      "plan": null,
      "speed": null,
      "expiry": null,
      "fields": [
        {
          "path": "data[0].downloaded",
          "label": "Data downloaded",
          "value": "22215090575",
          "display": "20.7 GB",
          "bytes": 22215090575
        },
        {
          "path": "data[0].uploaded",
          "label": "Data uploaded",
          "value": "4369204412",
          "display": "4.07 GB",
          "bytes": 4369204412
        }
      ],
      "daily_usage": [
        {
          "day": "2026-03-08",
          "download": 594257076,
          "upload": 381754073,
          "total": 976011149
        },
        {
          "day": "2026-03-09",
          "download": 17365677541,
          "upload": 5074272569,
          "total": 22439950110
        },
        {
          "day": "2026-03-10",
          "download": 13203570717,
          "upload": 2936530689,
          "total": 16140101406
        },
        {
          "day": "2026-03-11",
          "download": 13577557512,
          "upload": 2104851555,
          "total": 15682409067
        },
        {
          "day": "2026-03-12",
          "download": 13946847910,
          "upload": 5228426897,
          "total": 19175274807
        },
        {
          "day": "2026-03-13",
          "download": 5210009912,
          "upload": 1529843004,
          "total": 6739852916
        },
        {
          "day": "2026-03-14",
          "download": 3863391074,
          "upload": 885641838,
          "total": 4749032912
        },
        {
          "day": "2026-03-15",
          "download": 7653067771,
          "upload": 2280593028,
          "total": 9933660799
        },
        {
          "day": "2026-03-16",
          "download": 40108428659,
          "upload": 2687815056,
          "total": 42796243715
        },
        {
          "day": "2026-03-17",
          "download": 2256605332,
          "upload": 164160414,
          "total": 2420765746
        },
        {
          "day": "2026-03-18",
          "download": 20180984057,
          "upload": 3669828282,
          "total": 23850812339
        },
        {
          "day": "2026-03-19",
          "download": 20351445993,
          "upload": 2670664701,
          "total": 23022110694
        },
        {
          "day": "2026-03-20",
          "download": 7814131030,
          "upload": 714163583,
          "total": 8528294613
        },
        {
          "day": "2026-03-21",
          "download": 5997443276,
          "upload": 732089945,
          "total": 6729533221
        },
        {
          "day": "2026-03-22",
          "download": 7620411483,
          "upload": 2155583287,
          "total": 9775994770
        },
        {
          "day": "2026-03-23",
          "download": 7233014865,
          "upload": 1566896049,
          "total": 8799910914
        },
        {
          "day": "2026-03-24",
          "download": 6579239818,
          "upload": 1545314846,
          "total": 8124554664
        },
        {
          "day": "2026-03-25",
          "download": 13412554548,
          "upload": 3802069671,
          "total": 17214624219
        },
        {
          "day": "2026-03-26",
          "download": 12746267535,
          "upload": 1156770463,
          "total": 13903037998
        },
        {
          "day": "2026-03-27",
          "download": 6674806809,
          "upload": 605614687,
          "total": 7280421496
        },
        {
          "day": "2026-03-28",
          "download": 4503002447,
          "upload": 557101783,
          "total": 5060104230
        },
        {
          "day": "2026-03-29",
          "download": 12452965790,
          "upload": 1376190462,
          "total": 13829156252
        },
        {
          "day": "2026-03-30",
          "download": 17301581609,
          "upload": 1405139022,
          "total": 18706720631
        },
        {
          "day": "2026-03-31",
          "download": 3754932022,
          "upload": 183197067,
          "total": 3938129089
        },
        {
          "day": "2026-04-01",
          "download": 8682962360,
          "upload": 2264118741,
          "total": 10947081101
        },
        {
          "day": "2026-04-02",
          "download": 21998548676,
          "upload": 2046854261,
          "total": 24045402937
        },
        {
          "day": "2026-04-03",
          "download": 5787872163,
          "upload": 657033499,
          "total": 6444905662
        },
        {
          "day": "2026-04-04",
          "download": 7963811293,
          "upload": 760483766,
          "total": 8724295059
        },
        {
          "day": "2026-04-05",
          "download": 13143757647,
          "upload": 1972406248,
          "total": 15116163895
        },
        {
          "day": "2026-04-06",
          "download": 12283637900,
          "upload": 851465081,
          "total": 13135102981
        },
        {
          "day": "2026-04-07",
          "download": 10625877382,
          "upload": 1539038588,
          "total": 12164915970
        },
        {
          "day": "2026-04-08",
          "download": 2266060678,
          "upload": 84177284,
          "total": 2350237962
        },
        {
          "day": "2026-04-09",
          "download": 20376103662,
          "upload": 3680561834,
          "total": 24056665496
        },
        {
          "day": "2026-04-10",
          "download": 10065204916,
          "upload": 1061022433,
          "total": 11126227349
        },
        {
          "day": "2026-04-11",
          "download": 6668923294,
          "upload": 702179761,
          "total": 7371103055
        },
        {
          "day": "2026-04-12",
          "download": 2438318890,
          "upload": 116062630,
          "total": 2554381520
        },
        {
          "day": "2026-04-13",
          "download": 10424770167,
          "upload": 881230694,
          "total": 11306000861
        },
        {
          "day": "2026-04-14",
          "download": 12692477182,
          "upload": 1480551175,
          "total": 14173028357
        },
        {
          "day": "2026-04-15",
          "download": 10110156594,
          "upload": 928599950,
          "total": 11038756544
        },
        {
          "day": "2026-04-16",
          "download": 16371615547,
          "upload": 2048926302,
          "total": 18420541849
        },
        {
          "day": "2026-04-17",
          "download": 12314581181,
          "upload": 1456943363,
          "total": 13771524544
        },
        {
          "day": "2026-04-18",
          "download": 11710691754,
          "upload": 933807315,
          "total": 12644499069
        },
        {
          "day": "2026-04-19",
          "download": 10548462541,
          "upload": 1971007536,
          "total": 12519470077
        },
        {
          "day": "2026-04-20",
          "download": 3091192971,
          "upload": 417309115,
          "total": 3508502086
        },
        {
          "day": "2026-04-21",
          "download": 9077430,
          "upload": 100030437,
          "total": 109107867
        },
        {
          "day": "2026-04-22",
          "download": 4044268,
          "upload": 3393148,
          "total": 7437416
        },
        {
          "day": "2026-04-23",
          "download": 1612739,
          "upload": 1275300,
          "total": 2888039
        },
        {
          "day": "2026-04-24",
          "download": 3743153,
          "upload": 3423327,
          "total": 7166480
        },
        {
          "day": "2026-04-25",
          "download": 9994124,
          "upload": 14139778,
          "total": 24133902
        },
        {
          "day": "2026-04-26",
          "download": 5840914,
          "upload": 3439329,
          "total": 9280243
        },
        {
          "day": "2026-04-27",
          "download": 7343872,
          "upload": 13174747,
          "total": 20518619
        },
        {
          "day": "2026-04-28",
          "download": 2733757,
          "upload": 7827451,
          "total": 10561208
        },
        {
          "day": "2026-04-29",
          "download": 6069202,
          "upload": 6990822,
          "total": 13060024
        },
        {
          "day": "2026-04-30",
          "download": 7013687,
          "upload": 5579630,
          "total": 12593317
        },
        {
          "day": "2026-05-01",
          "download": 1560014067,
          "upload": 1292403131,
          "total": 2852417198
        },
        {
          "day": "2026-05-02",
          "download": 54005843062,
          "upload": 9058824311,
          "total": 63064667373
        },
        {
          "day": "2026-05-03",
          "download": 90073477423,
          "upload": 3916719778,
          "total": 93990197201
        },
        {
          "day": "2026-05-04",
          "download": 11344146766,
          "upload": 915630161,
          "total": 12259776927
        },
        {
          "day": "2026-05-05",
          "download": 38299942551,
          "upload": 2798635326,
          "total": 41098577877
        },
        {
          "day": "2026-05-06",
          "download": 17104893633,
          "upload": 1240480892,
          "total": 18345374525
        },
        {
          "day": "2026-05-07",
          "download": 74145153085,
          "upload": 5265222542,
          "total": 79410375627
        },
        {
          "day": "2026-05-08",
          "download": 79230849708,
          "upload": 3413456008,
          "total": 82644305716
        },
        {
          "day": "2026-05-09",
          "download": 13129279889,
          "upload": 1353191235,
          "total": 14482471124
        },
        {
          "day": "2026-05-10",
          "download": 6201504944,
          "upload": 2222114907,
          "total": 8423619851
        },
        {
          "day": "2026-05-11",
          "download": 8534724981,
          "upload": 4621114904,
          "total": 13155839885
        },
        {
          "day": "2026-05-12",
          "download": 69984741255,
          "upload": 4013581678,
          "total": 73998322933
        },
        {
          "day": "2026-05-13",
          "download": 13744751720,
          "upload": 1667725742,
          "total": 15412477462
        },
        {
          "day": "2026-05-14",
          "download": 102059542011,
          "upload": 7523611517,
          "total": 109583153528
        },
        {
          "day": "2026-05-15",
          "download": 11192357407,
          "upload": 1296384860,
          "total": 12488742267
        },
        {
          "day": "2026-05-16",
          "download": 11910598881,
          "upload": 767889397,
          "total": 12678488278
        },
        {
          "day": "2026-05-17",
          "download": 14440313888,
          "upload": 3267112165,
          "total": 17707426053
        },
        {
          "day": "2026-05-18",
          "download": 13686648835,
          "upload": 1678635561,
          "total": 15365284396
        },
        {
          "day": "2026-05-19",
          "download": 10517089368,
          "upload": 1953887062,
          "total": 12470976430
        },
        {
          "day": "2026-05-20",
          "download": 11956188150,
          "upload": 1268177086,
          "total": 13224365236
        },
        {
          "day": "2026-05-21",
          "download": 13119581242,
          "upload": 1989493036,
          "total": 15109074278
        },
        {
          "day": "2026-05-22",
          "download": 9826381394,
          "upload": 1107983867,
          "total": 10934365261
        },
        {
          "day": "2026-05-23",
          "download": 11659311285,
          "upload": 1697497961,
          "total": 13356809246
        },
        {
          "day": "2026-05-24",
          "download": 15715412818,
          "upload": 2940344509,
          "total": 18655757327
        },
        {
          "day": "2026-05-25",
          "download": 17837334664,
          "upload": 1455000423,
          "total": 19292335087
        },
        {
          "day": "2026-05-26",
          "download": 7319124422,
          "upload": 871016825,
          "total": 8190141247
        },
        {
          "day": "2026-05-27",
          "download": 38588231647,
          "upload": 2031091372,
          "total": 40619323019
        },
        {
          "day": "2026-05-28",
          "download": 15468621544,
          "upload": 2072388191,
          "total": 17541009735
        },
        {
          "day": "2026-05-29",
          "download": 19125480452,
          "upload": 2340932860,
          "total": 21466413312
        },
        {
          "day": "2026-05-30",
          "download": 50356443952,
          "upload": 2483972176,
          "total": 52840416128
        },
        {
          "day": "2026-05-31",
          "download": 20172068312,
          "upload": 1327763043,
          "total": 21499831355
        },
        {
          "day": "2026-06-01",
          "download": 10947413780,
          "upload": 2501481999,
          "total": 13448895779
        },
        {
          "day": "2026-06-02",
          "download": 16260466534,
          "upload": 2580265974,
          "total": 18840732508
        },
        {
          "day": "2026-06-03",
          "download": 16792042005,
          "upload": 3668225707,
          "total": 20460267712
        },
        {
          "day": "2026-06-04",
          "download": 2149495146,
          "upload": 504071619,
          "total": 2653566765
        },
        {
          "day": "2026-06-05",
          "download": 8750325983,
          "upload": 7265533519,
          "total": 16015859502
        },
        {
          "day": "2026-06-06",
          "download": 13778397207,
          "upload": 1315814954,
          "total": 15094212161
        },
        {
          "day": "2026-06-07",
          "download": 12488466027,
          "upload": 2226987247,
          "total": 14715453274
        },
        {
          "day": "2026-06-08",
          "download": 4530524824,
          "upload": 2716782708,
          "total": 7247307532
        },
        {
          "day": "2026-06-09",
          "download": 11569633241,
          "upload": 3646655645,
          "total": 15216288886
        },
        {
          "day": "2026-06-10",
          "download": 5420796588,
          "upload": 1797083546,
          "total": 7217880134
        },
        {
          "day": "2026-06-11",
          "download": 37864432991,
          "upload": 16778719436,
          "total": 54643152427
        },
        {
          "day": "2026-06-12",
          "download": 11621301783,
          "upload": 1442732211,
          "total": 13064033994
        },
        {
          "day": "2026-06-13",
          "download": 13969915336,
          "upload": 3926303786,
          "total": 17896219122
        },
        {
          "day": "2026-06-14",
          "download": 12167378736,
          "upload": 4021702582,
          "total": 16189081318
        },
        {
          "day": "2026-06-15",
          "download": 20533698716,
          "upload": 3062540410,
          "total": 23596239126
        },
        {
          "day": "2026-06-16",
          "download": 22215090575,
          "upload": 4369204412,
          "total": 26584294987
        }
      ]
    }
  },
  "history": [
    {
      "timestamp": "2026-06-18T20:35:31+05:30",
      "http_status": 200,
      "duration_ms": 195,
      "request_window": {
        "start_date": "2025-12-31T18:30:00.000Z",
        "end_date": "2026-06-18T15:05:31.730Z",
        "timezone": "Asia/Kolkata"
      },
      "normalized": {
        "total_used": null,
        "download": {
          "path": "data[0].downloaded",
          "label": "Data downloaded",
          "value": "22215090575",
          "display": "22215090575",
          "bytes": 22215090575
        },
        "upload": {
          "path": "data[0].uploaded",
          "label": "Data uploaded",
          "value": "4369204412",
          "display": "4369204412",
          "bytes": 4369204412
        },
        "remaining": null,
        "quota": null,
        "plan": null,
        "speed": null,
        "expiry": null,
        "fields": [
          {
            "path": "data[0].downloaded",
            "label": "Data downloaded",
            "value": "22215090575",
            "display": "20.7 GB",
            "bytes": 22215090575
          },
          {
            "path": "data[0].uploaded",
            "label": "Data uploaded",
            "value": "4369204412",
            "display": "4.07 GB",
            "bytes": 4369204412
          }
        ],
        "daily_usage": [
          {
            "day": "2026-03-08",
            "download": 594257076,
            "upload": 381754073,
            "total": 976011149
          },
          {
            "day": "2026-03-09",
            "download": 17365677541,
            "upload": 5074272569,
            "total": 22439950110
          },
          {
            "day": "2026-03-10",
            "download": 13203570717,
            "upload": 2936530689,
            "total": 16140101406
          },
          {
            "day": "2026-03-11",
            "download": 13577557512,
            "upload": 2104851555,
            "total": 15682409067
          },
          {
            "day": "2026-03-12",
            "download": 13946847910,
            "upload": 5228426897,
            "total": 19175274807
          },
          {
            "day": "2026-03-13",
            "download": 5210009912,
            "upload": 1529843004,
            "total": 6739852916
          },
          {
            "day": "2026-03-14",
            "download": 3863391074,
            "upload": 885641838,
            "total": 4749032912
          },
          {
            "day": "2026-03-15",
            "download": 7653067771,
            "upload": 2280593028,
            "total": 9933660799
          },
          {
            "day": "2026-03-16",
            "download": 40108428659,
            "upload": 2687815056,
            "total": 42796243715
          },
          {
            "day": "2026-03-17",
            "download": 2256605332,
            "upload": 164160414,
            "total": 2420765746
          },
          {
            "day": "2026-03-18",
            "download": 20180984057,
            "upload": 3669828282,
            "total": 23850812339
          },
          {
            "day": "2026-03-19",
            "download": 20351445993,
            "upload": 2670664701,
            "total": 23022110694
          },
          {
            "day": "2026-03-20",
            "download": 7814131030,
            "upload": 714163583,
            "total": 8528294613
          },
          {
            "day": "2026-03-21",
            "download": 5997443276,
            "upload": 732089945,
            "total": 6729533221
          },
          {
            "day": "2026-03-22",
            "download": 7620411483,
            "upload": 2155583287,
            "total": 9775994770
          },
          {
            "day": "2026-03-23",
            "download": 7233014865,
            "upload": 1566896049,
            "total": 8799910914
          },
          {
            "day": "2026-03-24",
            "download": 6579239818,
            "upload": 1545314846,
            "total": 8124554664
          },
          {
            "day": "2026-03-25",
            "download": 13412554548,
            "upload": 3802069671,
            "total": 17214624219
          },
          {
            "day": "2026-03-26",
            "download": 12746267535,
            "upload": 1156770463,
            "total": 13903037998
          },
          {
            "day": "2026-03-27",
            "download": 6674806809,
            "upload": 605614687,
            "total": 7280421496
          },
          {
            "day": "2026-03-28",
            "download": 4503002447,
            "upload": 557101783,
            "total": 5060104230
          },
          {
            "day": "2026-03-29",
            "download": 12452965790,
            "upload": 1376190462,
            "total": 13829156252
          },
          {
            "day": "2026-03-30",
            "download": 17301581609,
            "upload": 1405139022,
            "total": 18706720631
          },
          {
            "day": "2026-03-31",
            "download": 3754932022,
            "upload": 183197067,
            "total": 3938129089
          },
          {
            "day": "2026-04-01",
            "download": 8682962360,
            "upload": 2264118741,
            "total": 10947081101
          },
          {
            "day": "2026-04-02",
            "download": 21998548676,
            "upload": 2046854261,
            "total": 24045402937
          },
          {
            "day": "2026-04-03",
            "download": 5787872163,
            "upload": 657033499,
            "total": 6444905662
          },
          {
            "day": "2026-04-04",
            "download": 7963811293,
            "upload": 760483766,
            "total": 8724295059
          },
          {
            "day": "2026-04-05",
            "download": 13143757647,
            "upload": 1972406248,
            "total": 15116163895
          },
          {
            "day": "2026-04-06",
            "download": 12283637900,
            "upload": 851465081,
            "total": 13135102981
          },
          {
            "day": "2026-04-07",
            "download": 10625877382,
            "upload": 1539038588,
            "total": 12164915970
          },
          {
            "day": "2026-04-08",
            "download": 2266060678,
            "upload": 84177284,
            "total": 2350237962
          },
          {
            "day": "2026-04-09",
            "download": 20376103662,
            "upload": 3680561834,
            "total": 24056665496
          },
          {
            "day": "2026-04-10",
            "download": 10065204916,
            "upload": 1061022433,
            "total": 11126227349
          },
          {
            "day": "2026-04-11",
            "download": 6668923294,
            "upload": 702179761,
            "total": 7371103055
          },
          {
            "day": "2026-04-12",
            "download": 2438318890,
            "upload": 116062630,
            "total": 2554381520
          },
          {
            "day": "2026-04-13",
            "download": 10424770167,
            "upload": 881230694,
            "total": 11306000861
          },
          {
            "day": "2026-04-14",
            "download": 12692477182,
            "upload": 1480551175,
            "total": 14173028357
          },
          {
            "day": "2026-04-15",
            "download": 10110156594,
            "upload": 928599950,
            "total": 11038756544
          },
          {
            "day": "2026-04-16",
            "download": 16371615547,
            "upload": 2048926302,
            "total": 18420541849
          },
          {
            "day": "2026-04-17",
            "download": 12314581181,
            "upload": 1456943363,
            "total": 13771524544
          },
          {
            "day": "2026-04-18",
            "download": 11710691754,
            "upload": 933807315,
            "total": 12644499069
          },
          {
            "day": "2026-04-19",
            "download": 10548462541,
            "upload": 1971007536,
            "total": 12519470077
          },
          {
            "day": "2026-04-20",
            "download": 3091192971,
            "upload": 417309115,
            "total": 3508502086
          },
          {
            "day": "2026-04-21",
            "download": 9077430,
            "upload": 100030437,
            "total": 109107867
          },
          {
            "day": "2026-04-22",
            "download": 4044268,
            "upload": 3393148,
            "total": 7437416
          },
          {
            "day": "2026-04-23",
            "download": 1612739,
            "upload": 1275300,
            "total": 2888039
          },
          {
            "day": "2026-04-24",
            "download": 3743153,
            "upload": 3423327,
            "total": 7166480
          },
          {
            "day": "2026-04-25",
            "download": 9994124,
            "upload": 14139778,
            "total": 24133902
          },
          {
            "day": "2026-04-26",
            "download": 5840914,
            "upload": 3439329,
            "total": 9280243
          },
          {
            "day": "2026-04-27",
            "download": 7343872,
            "upload": 13174747,
            "total": 20518619
          },
          {
            "day": "2026-04-28",
            "download": 2733757,
            "upload": 7827451,
            "total": 10561208
          },
          {
            "day": "2026-04-29",
            "download": 6069202,
            "upload": 6990822,
            "total": 13060024
          },
          {
            "day": "2026-04-30",
            "download": 7013687,
            "upload": 5579630,
            "total": 12593317
          },
          {
            "day": "2026-05-01",
            "download": 1560014067,
            "upload": 1292403131,
            "total": 2852417198
          },
          {
            "day": "2026-05-02",
            "download": 54005843062,
            "upload": 9058824311,
            "total": 63064667373
          },
          {
            "day": "2026-05-03",
            "download": 90073477423,
            "upload": 3916719778,
            "total": 93990197201
          },
          {
            "day": "2026-05-04",
            "download": 11344146766,
            "upload": 915630161,
            "total": 12259776927
          },
          {
            "day": "2026-05-05",
            "download": 38299942551,
            "upload": 2798635326,
            "total": 41098577877
          },
          {
            "day": "2026-05-06",
            "download": 17104893633,
            "upload": 1240480892,
            "total": 18345374525
          },
          {
            "day": "2026-05-07",
            "download": 74145153085,
            "upload": 5265222542,
            "total": 79410375627
          },
          {
            "day": "2026-05-08",
            "download": 79230849708,
            "upload": 3413456008,
            "total": 82644305716
          },
          {
            "day": "2026-05-09",
            "download": 13129279889,
            "upload": 1353191235,
            "total": 14482471124
          },
          {
            "day": "2026-05-10",
            "download": 6201504944,
            "upload": 2222114907,
            "total": 8423619851
          },
          {
            "day": "2026-05-11",
            "download": 8534724981,
            "upload": 4621114904,
            "total": 13155839885
          },
          {
            "day": "2026-05-12",
            "download": 69984741255,
            "upload": 4013581678,
            "total": 73998322933
          },
          {
            "day": "2026-05-13",
            "download": 13744751720,
            "upload": 1667725742,
            "total": 15412477462
          },
          {
            "day": "2026-05-14",
            "download": 102059542011,
            "upload": 7523611517,
            "total": 109583153528
          },
          {
            "day": "2026-05-15",
            "download": 11192357407,
            "upload": 1296384860,
            "total": 12488742267
          },
          {
            "day": "2026-05-16",
            "download": 11910598881,
            "upload": 767889397,
            "total": 12678488278
          },
          {
            "day": "2026-05-17",
            "download": 14440313888,
            "upload": 3267112165,
            "total": 17707426053
          },
          {
            "day": "2026-05-18",
            "download": 13686648835,
            "upload": 1678635561,
            "total": 15365284396
          },
          {
            "day": "2026-05-19",
            "download": 10517089368,
            "upload": 1953887062,
            "total": 12470976430
          },
          {
            "day": "2026-05-20",
            "download": 11956188150,
            "upload": 1268177086,
            "total": 13224365236
          },
          {
            "day": "2026-05-21",
            "download": 13119581242,
            "upload": 1989493036,
            "total": 15109074278
          },
          {
            "day": "2026-05-22",
            "download": 9826381394,
            "upload": 1107983867,
            "total": 10934365261
          },
          {
            "day": "2026-05-23",
            "download": 11659311285,
            "upload": 1697497961,
            "total": 13356809246
          },
          {
            "day": "2026-05-24",
            "download": 15715412818,
            "upload": 2940344509,
            "total": 18655757327
          },
          {
            "day": "2026-05-25",
            "download": 17837334664,
            "upload": 1455000423,
            "total": 19292335087
          },
          {
            "day": "2026-05-26",
            "download": 7319124422,
            "upload": 871016825,
            "total": 8190141247
          },
          {
            "day": "2026-05-27",
            "download": 38588231647,
            "upload": 2031091372,
            "total": 40619323019
          },
          {
            "day": "2026-05-28",
            "download": 15468621544,
            "upload": 2072388191,
            "total": 17541009735
          },
          {
            "day": "2026-05-29",
            "download": 19125480452,
            "upload": 2340932860,
            "total": 21466413312
          },
          {
            "day": "2026-05-30",
            "download": 50356443952,
            "upload": 2483972176,
            "total": 52840416128
          },
          {
            "day": "2026-05-31",
            "download": 20172068312,
            "upload": 1327763043,
            "total": 21499831355
          },
          {
            "day": "2026-06-01",
            "download": 10947413780,
            "upload": 2501481999,
            "total": 13448895779
          },
          {
            "day": "2026-06-02",
            "download": 16260466534,
            "upload": 2580265974,
            "total": 18840732508
          },
          {
            "day": "2026-06-03",
            "download": 16792042005,
            "upload": 3668225707,
            "total": 20460267712
          },
          {
            "day": "2026-06-04",
            "download": 2149495146,
            "upload": 504071619,
            "total": 2653566765
          },
          {
            "day": "2026-06-05",
            "download": 8750325983,
            "upload": 7265533519,
            "total": 16015859502
          },
          {
            "day": "2026-06-06",
            "download": 13778397207,
            "upload": 1315814954,
            "total": 15094212161
          },
          {
            "day": "2026-06-07",
            "download": 12488466027,
            "upload": 2226987247,
            "total": 14715453274
          },
          {
            "day": "2026-06-08",
            "download": 4530524824,
            "upload": 2716782708,
            "total": 7247307532
          },
          {
            "day": "2026-06-09",
            "download": 11569633241,
            "upload": 3646655645,
            "total": 15216288886
          },
          {
            "day": "2026-06-10",
            "download": 5420796588,
            "upload": 1797083546,
            "total": 7217880134
          },
          {
            "day": "2026-06-11",
            "download": 37864432991,
            "upload": 16778719436,
            "total": 54643152427
          },
          {
            "day": "2026-06-12",
            "download": 11621301783,
            "upload": 1442732211,
            "total": 13064033994
          },
          {
            "day": "2026-06-13",
            "download": 13969915336,
            "upload": 3926303786,
            "total": 17896219122
          },
          {
            "day": "2026-06-14",
            "download": 12167378736,
            "upload": 4021702582,
            "total": 16189081318
          },
          {
            "day": "2026-06-15",
            "download": 20533698716,
            "upload": 3062540410,
            "total": 23596239126
          },
          {
            "day": "2026-06-16",
            "download": 22215090575,
            "upload": 4369204412,
            "total": 26584294987
          }
        ]
      }
    },
    {
      "timestamp": "2026-06-18T20:38:07+05:30",
      "http_status": 200,
      "duration_ms": 225,
      "request_window": {
        "start_date": "2025-12-31T18:30:00.000Z",
        "end_date": "2026-06-18T15:08:06.940Z",
        "timezone": "Asia/Kolkata"
      },
      "normalized": {
        "total_used": null,
        "download": {
          "path": "data[0].downloaded",
          "label": "Data downloaded",
          "value": "22215090575",
          "display": "22215090575",
          "bytes": 22215090575
        },
        "upload": {
          "path": "data[0].uploaded",
          "label": "Data uploaded",
          "value": "4369204412",
          "display": "4369204412",
          "bytes": 4369204412
        },
        "remaining": null,
        "quota": null,
        "plan": null,
        "speed": null,
        "expiry": null,
        "fields": [
          {
            "path": "data[0].downloaded",
            "label": "Data downloaded",
            "value": "22215090575",
            "display": "20.7 GB",
            "bytes": 22215090575
          },
          {
            "path": "data[0].uploaded",
            "label": "Data uploaded",
            "value": "4369204412",
            "display": "4.07 GB",
            "bytes": 4369204412
          }
        ],
        "daily_usage": [
          {
            "day": "2026-03-08",
            "download": 594257076,
            "upload": 381754073,
            "total": 976011149
          },
          {
            "day": "2026-03-09",
            "download": 17365677541,
            "upload": 5074272569,
            "total": 22439950110
          },
          {
            "day": "2026-03-10",
            "download": 13203570717,
            "upload": 2936530689,
            "total": 16140101406
          },
          {
            "day": "2026-03-11",
            "download": 13577557512,
            "upload": 2104851555,
            "total": 15682409067
          },
          {
            "day": "2026-03-12",
            "download": 13946847910,
            "upload": 5228426897,
            "total": 19175274807
          },
          {
            "day": "2026-03-13",
            "download": 5210009912,
            "upload": 1529843004,
            "total": 6739852916
          },
          {
            "day": "2026-03-14",
            "download": 3863391074,
            "upload": 885641838,
            "total": 4749032912
          },
          {
            "day": "2026-03-15",
            "download": 7653067771,
            "upload": 2280593028,
            "total": 9933660799
          },
          {
            "day": "2026-03-16",
            "download": 40108428659,
            "upload": 2687815056,
            "total": 42796243715
          },
          {
            "day": "2026-03-17",
            "download": 2256605332,
            "upload": 164160414,
            "total": 2420765746
          },
          {
            "day": "2026-03-18",
            "download": 20180984057,
            "upload": 3669828282,
            "total": 23850812339
          },
          {
            "day": "2026-03-19",
            "download": 20351445993,
            "upload": 2670664701,
            "total": 23022110694
          },
          {
            "day": "2026-03-20",
            "download": 7814131030,
            "upload": 714163583,
            "total": 8528294613
          },
          {
            "day": "2026-03-21",
            "download": 5997443276,
            "upload": 732089945,
            "total": 6729533221
          },
          {
            "day": "2026-03-22",
            "download": 7620411483,
            "upload": 2155583287,
            "total": 9775994770
          },
          {
            "day": "2026-03-23",
            "download": 7233014865,
            "upload": 1566896049,
            "total": 8799910914
          },
          {
            "day": "2026-03-24",
            "download": 6579239818,
            "upload": 1545314846,
            "total": 8124554664
          },
          {
            "day": "2026-03-25",
            "download": 13412554548,
            "upload": 3802069671,
            "total": 17214624219
          },
          {
            "day": "2026-03-26",
            "download": 12746267535,
            "upload": 1156770463,
            "total": 13903037998
          },
          {
            "day": "2026-03-27",
            "download": 6674806809,
            "upload": 605614687,
            "total": 7280421496
          },
          {
            "day": "2026-03-28",
            "download": 4503002447,
            "upload": 557101783,
            "total": 5060104230
          },
          {
            "day": "2026-03-29",
            "download": 12452965790,
            "upload": 1376190462,
            "total": 13829156252
          },
          {
            "day": "2026-03-30",
            "download": 17301581609,
            "upload": 1405139022,
            "total": 18706720631
          },
          {
            "day": "2026-03-31",
            "download": 3754932022,
            "upload": 183197067,
            "total": 3938129089
          },
          {
            "day": "2026-04-01",
            "download": 8682962360,
            "upload": 2264118741,
            "total": 10947081101
          },
          {
            "day": "2026-04-02",
            "download": 21998548676,
            "upload": 2046854261,
            "total": 24045402937
          },
          {
            "day": "2026-04-03",
            "download": 5787872163,
            "upload": 657033499,
            "total": 6444905662
          },
          {
            "day": "2026-04-04",
            "download": 7963811293,
            "upload": 760483766,
            "total": 8724295059
          },
          {
            "day": "2026-04-05",
            "download": 13143757647,
            "upload": 1972406248,
            "total": 15116163895
          },
          {
            "day": "2026-04-06",
            "download": 12283637900,
            "upload": 851465081,
            "total": 13135102981
          },
          {
            "day": "2026-04-07",
            "download": 10625877382,
            "upload": 1539038588,
            "total": 12164915970
          },
          {
            "day": "2026-04-08",
            "download": 2266060678,
            "upload": 84177284,
            "total": 2350237962
          },
          {
            "day": "2026-04-09",
            "download": 20376103662,
            "upload": 3680561834,
            "total": 24056665496
          },
          {
            "day": "2026-04-10",
            "download": 10065204916,
            "upload": 1061022433,
            "total": 11126227349
          },
          {
            "day": "2026-04-11",
            "download": 6668923294,
            "upload": 702179761,
            "total": 7371103055
          },
          {
            "day": "2026-04-12",
            "download": 2438318890,
            "upload": 116062630,
            "total": 2554381520
          },
          {
            "day": "2026-04-13",
            "download": 10424770167,
            "upload": 881230694,
            "total": 11306000861
          },
          {
            "day": "2026-04-14",
            "download": 12692477182,
            "upload": 1480551175,
            "total": 14173028357
          },
          {
            "day": "2026-04-15",
            "download": 10110156594,
            "upload": 928599950,
            "total": 11038756544
          },
          {
            "day": "2026-04-16",
            "download": 16371615547,
            "upload": 2048926302,
            "total": 18420541849
          },
          {
            "day": "2026-04-17",
            "download": 12314581181,
            "upload": 1456943363,
            "total": 13771524544
          },
          {
            "day": "2026-04-18",
            "download": 11710691754,
            "upload": 933807315,
            "total": 12644499069
          },
          {
            "day": "2026-04-19",
            "download": 10548462541,
            "upload": 1971007536,
            "total": 12519470077
          },
          {
            "day": "2026-04-20",
            "download": 3091192971,
            "upload": 417309115,
            "total": 3508502086
          },
          {
            "day": "2026-04-21",
            "download": 9077430,
            "upload": 100030437,
            "total": 109107867
          },
          {
            "day": "2026-04-22",
            "download": 4044268,
            "upload": 3393148,
            "total": 7437416
          },
          {
            "day": "2026-04-23",
            "download": 1612739,
            "upload": 1275300,
            "total": 2888039
          },
          {
            "day": "2026-04-24",
            "download": 3743153,
            "upload": 3423327,
            "total": 7166480
          },
          {
            "day": "2026-04-25",
            "download": 9994124,
            "upload": 14139778,
            "total": 24133902
          },
          {
            "day": "2026-04-26",
            "download": 5840914,
            "upload": 3439329,
            "total": 9280243
          },
          {
            "day": "2026-04-27",
            "download": 7343872,
            "upload": 13174747,
            "total": 20518619
          },
          {
            "day": "2026-04-28",
            "download": 2733757,
            "upload": 7827451,
            "total": 10561208
          },
          {
            "day": "2026-04-29",
            "download": 6069202,
            "upload": 6990822,
            "total": 13060024
          },
          {
            "day": "2026-04-30",
            "download": 7013687,
            "upload": 5579630,
            "total": 12593317
          },
          {
            "day": "2026-05-01",
            "download": 1560014067,
            "upload": 1292403131,
            "total": 2852417198
          },
          {
            "day": "2026-05-02",
            "download": 54005843062,
            "upload": 9058824311,
            "total": 63064667373
          },
          {
            "day": "2026-05-03",
            "download": 90073477423,
            "upload": 3916719778,
            "total": 93990197201
          },
          {
            "day": "2026-05-04",
            "download": 11344146766,
            "upload": 915630161,
            "total": 12259776927
          },
          {
            "day": "2026-05-05",
            "download": 38299942551,
            "upload": 2798635326,
            "total": 41098577877
          },
          {
            "day": "2026-05-06",
            "download": 17104893633,
            "upload": 1240480892,
            "total": 18345374525
          },
          {
            "day": "2026-05-07",
            "download": 74145153085,
            "upload": 5265222542,
            "total": 79410375627
          },
          {
            "day": "2026-05-08",
            "download": 79230849708,
            "upload": 3413456008,
            "total": 82644305716
          },
          {
            "day": "2026-05-09",
            "download": 13129279889,
            "upload": 1353191235,
            "total": 14482471124
          },
          {
            "day": "2026-05-10",
            "download": 6201504944,
            "upload": 2222114907,
            "total": 8423619851
          },
          {
            "day": "2026-05-11",
            "download": 8534724981,
            "upload": 4621114904,
            "total": 13155839885
          },
          {
            "day": "2026-05-12",
            "download": 69984741255,
            "upload": 4013581678,
            "total": 73998322933
          },
          {
            "day": "2026-05-13",
            "download": 13744751720,
            "upload": 1667725742,
            "total": 15412477462
          },
          {
            "day": "2026-05-14",
            "download": 102059542011,
            "upload": 7523611517,
            "total": 109583153528
          },
          {
            "day": "2026-05-15",
            "download": 11192357407,
            "upload": 1296384860,
            "total": 12488742267
          },
          {
            "day": "2026-05-16",
            "download": 11910598881,
            "upload": 767889397,
            "total": 12678488278
          },
          {
            "day": "2026-05-17",
            "download": 14440313888,
            "upload": 3267112165,
            "total": 17707426053
          },
          {
            "day": "2026-05-18",
            "download": 13686648835,
            "upload": 1678635561,
            "total": 15365284396
          },
          {
            "day": "2026-05-19",
            "download": 10517089368,
            "upload": 1953887062,
            "total": 12470976430
          },
          {
            "day": "2026-05-20",
            "download": 11956188150,
            "upload": 1268177086,
            "total": 13224365236
          },
          {
            "day": "2026-05-21",
            "download": 13119581242,
            "upload": 1989493036,
            "total": 15109074278
          },
          {
            "day": "2026-05-22",
            "download": 9826381394,
            "upload": 1107983867,
            "total": 10934365261
          },
          {
            "day": "2026-05-23",
            "download": 11659311285,
            "upload": 1697497961,
            "total": 13356809246
          },
          {
            "day": "2026-05-24",
            "download": 15715412818,
            "upload": 2940344509,
            "total": 18655757327
          },
          {
            "day": "2026-05-25",
            "download": 17837334664,
            "upload": 1455000423,
            "total": 19292335087
          },
          {
            "day": "2026-05-26",
            "download": 7319124422,
            "upload": 871016825,
            "total": 8190141247
          },
          {
            "day": "2026-05-27",
            "download": 38588231647,
            "upload": 2031091372,
            "total": 40619323019
          },
          {
            "day": "2026-05-28",
            "download": 15468621544,
            "upload": 2072388191,
            "total": 17541009735
          },
          {
            "day": "2026-05-29",
            "download": 19125480452,
            "upload": 2340932860,
            "total": 21466413312
          },
          {
            "day": "2026-05-30",
            "download": 50356443952,
            "upload": 2483972176,
            "total": 52840416128
          },
          {
            "day": "2026-05-31",
            "download": 20172068312,
            "upload": 1327763043,
            "total": 21499831355
          },
          {
            "day": "2026-06-01",
            "download": 10947413780,
            "upload": 2501481999,
            "total": 13448895779
          },
          {
            "day": "2026-06-02",
            "download": 16260466534,
            "upload": 2580265974,
            "total": 18840732508
          },
          {
            "day": "2026-06-03",
            "download": 16792042005,
            "upload": 3668225707,
            "total": 20460267712
          },
          {
            "day": "2026-06-04",
            "download": 2149495146,
            "upload": 504071619,
            "total": 2653566765
          },
          {
            "day": "2026-06-05",
            "download": 8750325983,
            "upload": 7265533519,
            "total": 16015859502
          },
          {
            "day": "2026-06-06",
            "download": 13778397207,
            "upload": 1315814954,
            "total": 15094212161
          },
          {
            "day": "2026-06-07",
            "download": 12488466027,
            "upload": 2226987247,
            "total": 14715453274
          },
          {
            "day": "2026-06-08",
            "download": 4530524824,
            "upload": 2716782708,
            "total": 7247307532
          },
          {
            "day": "2026-06-09",
            "download": 11569633241,
            "upload": 3646655645,
            "total": 15216288886
          },
          {
            "day": "2026-06-10",
            "download": 5420796588,
            "upload": 1797083546,
            "total": 7217880134
          },
          {
            "day": "2026-06-11",
            "download": 37864432991,
            "upload": 16778719436,
            "total": 54643152427
          },
          {
            "day": "2026-06-12",
            "download": 11621301783,
            "upload": 1442732211,
            "total": 13064033994
          },
          {
            "day": "2026-06-13",
            "download": 13969915336,
            "upload": 3926303786,
            "total": 17896219122
          },
          {
            "day": "2026-06-14",
            "download": 12167378736,
            "upload": 4021702582,
            "total": 16189081318
          },
          {
            "day": "2026-06-15",
            "download": 20533698716,
            "upload": 3062540410,
            "total": 23596239126
          },
          {
            "day": "2026-06-16",
            "download": 22215090575,
            "upload": 4369204412,
            "total": 26584294987
          }
        ]
      }
    }
  ]
}
